[{},{"id":1,"name":"世界へ","conditions":[],"list":[{"code":112,"parameters":[0,71,0]},{"code":101,"parameters":[0,1,33,199,0,0]}],"trigger":0},{"id":2,"name":"扉１","conditions":[{"type":2,"param1":57,"param2":1,"compare":7}],"list":[{"code":13,"parameters":[54,54,0,0,1,0]},{"code":13,"parameters":[74,74,0,0,1,0]},{"code":13,"parameters":[75,75,0,0,52,0]},{"code":13,"parameters":[76,76,0,0,56,0]},{"code":112,"parameters":[0,40]}],"trigger":0},{"id":3,"name":"扉２","conditions":[{"type":2,"param1":57,"param2":2,"compare":7}],"list":[{"code":13,"parameters":[54,54,0,0,1,0]},{"code":13,"parameters":[74,74,0,0,2,0]},{"code":13,"parameters":[75,75,0,0,52,0]},{"code":13,"parameters":[76,76,0,0,56,0]},{"code":112,"parameters":[0,40]}]},{"id":4,"name":"宝３１","conditions":[{"type":0,"param1":61,"param2":0,"compare":0}],"list":[{"code":13,"parameters":[71,71,0,0,61,0,0]},{"code":13,"parameters":[73,73,0,0,10,0,0]},{"code":112,"parameters":[0,90,0]}]},{"id":5,"name":"宝３２","conditions":[{"type":0,"param1":62,"param2":0,"compare":0}],"list":[{"code":13,"parameters":[71,71,0,0,62,0,0]},{"code":13,"parameters":[73,73,0,0,44,0,0]},{"code":112,"parameters":[0,90,0]}]},{"id":6,"name":"神官","conditions":[],"list":[{"code":112,"parameters":[0,21,0]},{"code":13,"parameters":[11,11,0,2,26,0,0]},{"code":33,"parameters":[11,3,0,0]},{"code":51,"parameters":[0]},{"code":111,"parameters":[0,8,0]},{"code":58,"parameters":[]},{"code":53,"parameters":[]},{"code":111,"parameters":[0,9,0]},{"code":33,"parameters":[13,3,0,0]},{"code":51,"parameters":[0]},{"code":111,"parameters":[0,10,0]},{"code":58,"parameters":[]},{"code":53,"parameters":[]},{"code":1,"parameters":["※「うさぎ王国への　道を開くには\n３つの　うさぎの宝を\n集めなければ　なりません。",0]},{"code":1,"parameters":["※「それぞれの宝は　ナクリアル\nイトランド　ドレイスの　３つの王国が\n治めています。",0]},{"code":1,"parameters":["※「すべての宝を　集めたとき\n再び私の元を　訪ねなさい。\nきっと力に　なれるでしょう。",0]}]},{"id":7,"name":"案内","conditions":[],"list":[{"code":112,"parameters":[0,21,0]},{"code":1,"parameters":["※「ここは　古の神殿。\nうさぎ王国の　ことなら\n奥の　神官様に　聞くといいだろう。",0]}]},{"id":8,"name":"合成済みセリフ","conditions":[],"list":[{"code":14,"parameters":[2,1,50,0,0]},{"code":1,"parameters":["※「\\s[2]を　シュタージ北の\n岩山に　差し込むのです。",0]},{"code":1,"parameters":["※「そうすれば　うさぎ王国への道が\n開かれるでしょう。",0]}]},{"id":9,"name":"うさぎシリーズ確認","conditions":[],"list":[{"code":13,"parameters":[13,13,0,0,0,0,0]},{"code":13,"parameters":[11,11,0,0,-1,0,0]},{"code":15,"parameters":[12,4,11,105]},{"code":33,"parameters":[12,4,0,1]},{"code":51,"parameters":[0]},{"code":58,"parameters":[]},{"code":53,"parameters":[]},{"code":15,"parameters":[12,4,11,106]},{"code":33,"parameters":[12,4,0,1]},{"code":51,"parameters":[0]},{"code":58,"parameters":[]},{"code":53,"parameters":[]},{"code":15,"parameters":[12,4,11,107]},{"code":33,"parameters":[12,4,0,1]},{"code":51,"parameters":[0]},{"code":58,"parameters":[]},{"code":53,"parameters":[]},{"code":13,"parameters":[13,13,0,0,1,0,0]}]},{"id":10,"name":"合成","conditions":[],"list":[{"code":14,"parameters":[21,1,105,0,0]},{"code":14,"parameters":[22,1,106,0,0]},{"code":14,"parameters":[23,1,107,0,0]},{"code":1,"parameters":["※「\\s[21]　\\s[22]\nそして　\\s[23]を\n集めてきたようですね。",0]},{"code":1,"parameters":["※「これから　３つを　合成して\n本来の姿に　戻します。",0]},{"code":1,"parameters":["※「再び　分けることは　できません。\n合成しますか？",0]},{"code":112,"parameters":[0,13,0]},{"code":51,"parameters":[0]},{"code":1,"parameters":["※「それでは　うさぎの宝を\n置いてください。",0]},{"code":3,"parameters":[81]},{"code":53,"parameters":[]},{"code":52,"parameters":[]},{"code":1,"parameters":["※「迷っているのですか。\nいいでしょう。\n決心がついたら　またおいでなさい。",0]},{"code":58,"parameters":[]},{"code":53,"parameters":[]},{"code":112,"parameters":[0,23,0]},{"code":15,"parameters":[24,7,0,0]},{"code":1,"parameters":["\\s[24]は　\\s[21]\n\\s[22]　そして　\\s[23]を\n置いた。",0]},{"code":5,"parameters":[0]},{"code":13,"parameters":[71,71,0,0,0,0,0]},{"code":13,"parameters":[74,74,0,0,-1,0,0]},{"code":112,"parameters":[0,131,0]},{"code":112,"parameters":[0,21,0]},{"code":1,"parameters":["※「本来の姿　\\s[25]に\nもどりました。\nさあ　行きなさい。",0]},{"code":111,"parameters":[0,8,0]}]}]